converter_package_Louise/__init__.py
converter_package_Louise/converter.py
converter_package_louise-0.0.1.dist-info/METADATA
converter_package_louise-0.0.1.dist-info/WHEEL
converter_package_louise-0.0.1.dist-info/licenses/LICENSE
converter_package_louise-0.0.1.dist-info/RECORD
