Metadata-Version: 2.1
Name: converter_package_Louise
Version: 0.0.1
Summary: A small example package
Project-URL: Homepage, https://github.com/Lou13213/M1-2022-git-workflow
Project-URL: Bug Tracker, https://github.com/Lou13213/M1-2022-git-workflow/issues
Author-email: Louise <author@example.com>
License-File: LICENSE
Classifier: License :: OSI Approved :: MIT License
Classifier: Operating System :: OS Independent
Classifier: Programming Language :: Python :: 3
Requires-Python: >=3.7
